mumpspy/__init__.py
mumpspy/mumps_lib_c_struc.py
mumpspy/mumpspy.py
mumpspy-1.3.3.dist-info/LICENSE
mumpspy-1.3.3.dist-info/METADATA
mumpspy-1.3.3.dist-info/WHEEL
mumpspy-1.3.3.dist-info/top_level.txt
mumpspy-1.3.3.dist-info/RECORD
