Metadata-Version: 2.1
Name: mumpspy
Version: 1.3.3
Summary: MUMPS for Python
Author-email: Vladimír Lukeš <vlukes@kme.zcu.cz>
License: MIT License
Project-URL: homepage, https://github.com/vlukes/mumpspy
Keywords: sparse,solver
Classifier: Development Status :: 4 - Beta
Classifier: Intended Audience :: Developers
Classifier: Topic :: Scientific/Engineering :: Mathematics
Classifier: Programming Language :: Python
Classifier: License :: OSI Approved :: MIT License
Requires-Python: >=3.8
License-File: LICENSE
Requires-Dist: mpi4py
Requires-Dist: numpy
